euchrelib/__init__.py
euchrelib/deck.py
euchrelib/game.py
euchrelib/data/animals.txt
euchrelib-0.0.2.dist-info/LICENSE
euchrelib-0.0.2.dist-info/METADATA
euchrelib-0.0.2.dist-info/WHEEL
euchrelib-0.0.2.dist-info/top_level.txt
euchrelib-0.0.2.dist-info/RECORD
